alyssum/__init__.py
alyssum/cleaners.py
alyssum/decorators.py
alyssum/seperators.py
alyssum/settings.py
alyssum-0.0.14.dist-info/LICENCE.txt
alyssum-0.0.14.dist-info/METADATA
alyssum-0.0.14.dist-info/WHEEL
alyssum-0.0.14.dist-info/top_level.txt
alyssum-0.0.14.dist-info/RECORD
