Metadata-Version: 2.1
Name: alyssum
Version: 0.0.14
Summary: A small helper package for personal needs
Home-page: https://github.com/eaybek/alyssum
Author: Erdem Aybek
Author-email: eaybek@gmail.com
License: UNKNOWN
Platform: UNKNOWN
Classifier: Development Status :: 1 - Planning
Classifier: Programming Language :: Python :: 3
Classifier: License :: OSI Approved :: MIT License
Classifier: Operating System :: OS Independent
Requires-Dist: termcolor
